rapidocr_mcp/__init__.py
rapidocr_mcp/main.py
rapidocr_mcp-0.4.0.dist-info/METADATA
rapidocr_mcp-0.4.0.dist-info/WHEEL
rapidocr_mcp-0.4.0.dist-info/entry_points.txt
rapidocr_mcp-0.4.0.dist-info/licenses/LICENSE.txt
rapidocr_mcp-0.4.0.dist-info/RECORD
