Metadata-Version: 2.4
Name: rapidocr-mcp
Version: 0.4.0
Summary: RapidOCR MCP Server for OCR processing
Project-URL: Homepage, https://github.com/z4none/rapidocr-mcp
Project-URL: Repository, https://github.com/z4none/rapidocr-mcp.git
Author-email: z4none <z4none@gmail.com>
License-Expression: MIT
License-File: LICENSE.txt
Keywords: mcp,ocr,rapidocr
Requires-Python: >=3.13
Requires-Dist: mcp[cli]>=1.4.1
Requires-Dist: onnxruntime>=1.21.0
Requires-Dist: rapidocr>=2.0.3
Requires-Dist: requests>=2.32.3
